{"meta":{"id":"p163","name":"刘弇","dynasty":"song","category":"song","poemCount":535,"desc":"刘弇（一○四八～一一○二），字伟明，吉州安福（今属江西）人。神宗元丰二年（一○七九）进士，授通州海门主簿，调临颍令、洪州教授。哲宗绍圣二年（一○九五）知嘉州峨眉县。继中博学宏词科，改太学博士。元符中，因进《南郊大礼赋》，除秘书省正字。徽宗即位，改秘书省著作佐郎、充实录院检讨官。崇宁元年卒，年五十五。有《龙云先生文集》三十二卷。事见宋李彦弼《刘伟明墓志铭》（《龙云集》附录），《宋史》卷四四四有传。刘弇诗，以明弘治十八年刘璋刻《龙云先生文集》为底本（藏南京图书馆）。参校清乾隆十三年刊本（简称干本，藏江西省图书馆）、影印文渊阁四库全书本（简称四库本）、八千卷楼旧藏清钞本（简称八本，藏南京图书馆）、嘉业堂旧藏清钞本（简称嘉本，藏上海复旦大学图书馆）、民国涵芬楼刊印《宋诗钞补》（简称钞补本），并采用《豫章丛书》中《龙云集》胡思敬校记（简称胡校）。新辑得集外断句一联，附于卷末。"},"bodyChunkSize":128,"poems":[{"title":"赠贾仲武"},{"title":"元丰辛酉七月九夜大风四十韵"},{"title":"同朱彦周游元阳洞兼示文吴二羽人"},{"title":"仪真吕明父席中观新曲"},{"title":"送方绚解元赴试南宫用桂林一枝荆山片玉为韵八首  其一"},{"title":"送方绚解元赴试南宫用桂林一枝荆山片玉为韵八首  其二"},{"title":"送方绚解元赴试南宫用桂林一枝荆山片玉为韵八首  其三"},{"title":"送方绚解元赴试南宫用桂林一枝荆山片玉为韵八首  其四"},{"title":"送方绚解元赴试南宫用桂林一枝荆山片玉为韵八首  其五"},{"title":"送方绚解元赴试南宫用桂林一枝荆山片玉为韵八首  其六"},{"title":"送方绚解元赴试南宫用桂林一枝荆山片玉为韵八首  其七"},{"title":"送方绚解元赴试南宫用桂林一枝荆山片玉为韵八首  其八"},{"title":"古风谢汪都讲示惜惜吟"},{"title":"癸酉岁暮寿春道中五首  其一"},{"title":"癸酉岁暮寿春道中五首  其二"},{"title":"癸酉岁暮寿春道中五首  其三"},{"title":"癸酉岁暮寿春道中五首  其四"},{"title":"癸酉岁暮寿春道中五首  其五"},{"title":"建阳县二首  其一"},{"title":"建阳县二首  其二"},{"title":"赠相掌文廖生一首"},{"title":"赠廖相手一首"},{"title":"走笔答郭子隆勾稽"},{"title":"送李侯朝散还任一首"},{"title":"寄李彦弼端臣"},{"title":"石廊洞"},{"title":"同杨方士弭楫圆潭漩因赋诗即事"},{"title":"次韵和毛正仲胡潜画鹤歌"},{"title":"李宰新成假山"},{"title":"游浮洲寺寒林亭"},{"title":"黄鱼鲊寄狄复之因佐以诗"},{"title":"石港高侯见遗雏鹤辄成十五韵"},{"title":"送李令如堤上部夫"},{"title":"忆昨"},{"title":"人日"},{"title":"同李端臣游荐福寺禅院"},{"title":"叙旧赠董承君"},{"title":"送邢清臣赴左选"},{"title":"送真藏主赴泐潭干老会中"},{"title":"赠前住瑞竹寔禅师"},{"title":"丫头岩"},{"title":"车盘岭"},{"title":"过紫溪驿读黄安中中丞留题"},{"title":"宿孙彦傃舍居"},{"title":"宿法藏禅院二首  其一"},{"title":"宿法藏禅院二首  其二"},{"title":"清思"},{"title":"忆黄天倪"},{"title":"村南"},{"title":"安成道中作六首  其一"},{"title":"安成道中作六首  其二"},{"title":"安成道中作六首  其三"},{"title":"安成道中作六首  其四"},{"title":"安成道中作六首  其五"},{"title":"安成道中作六首  其六"},{"title":"夜叹"},{"title":"送曾该"},{"title":"畏日三首  其一"},{"title":"畏日三首  其二"},{"title":"畏日三首  其三"},{"title":"杉溪驿"},{"title":"送席延昌奉议"},{"title":"赠法云守光上人"},{"title":"黄洴"},{"title":"北禅水阁走笔"},{"title":"感寓二十首  其一"},{"title":"感寓二十首  其二"},{"title":"感寓二十首  其三"},{"title":"感寓二十首  其四"},{"title":"感寓二十首  其五"},{"title":"感寓二十首  其六"},{"title":"感寓二十首  其七"},{"title":"感寓二十首  其八"},{"title":"感寓二十首  其九"},{"title":"感寓二十首  其一○"},{"title":"感寓二十首  其一一"},{"title":"感寓二十首  其一二"},{"title":"感寓二十首  其一三"},{"title":"感寓二十首  其一四"},{"title":"感寓二十首  其一五"},{"title":"感寓二十首  其一六"},{"title":"感寓二十首  其一七"},{"title":"感寓二十首  其一八"},{"title":"感寓二十首  其一九"},{"title":"感寓二十首  其二○"},{"title":"秋日仪真即事十首  其一"},{"title":"秋日仪真即事十首  其二"},{"title":"秋日仪真即事十首  其三"},{"title":"秋日仪真即事十首  其四"},{"title":"秋日仪真即事十首  其五"},{"title":"秋日仪真即事十首  其六"},{"title":"秋日仪真即事十首  其七"},{"title":"秋日仪真即事十首  其八"},{"title":"秋日仪真即事十首  其九"},{"title":"秋日仪真即事十首  其一○"},{"title":"过东流圣感寺"},{"title":"按田行"},{"title":"持钓"},{"title":"宿长山寺二首  其一"},{"title":"宿长山寺二首  其二"},{"title":"游麻姑观用黄道士韵"},{"title":"夜泊玉湖口"},{"title":"桃叶行"},{"title":"何塘精舍"},{"title":"永新法云上方"},{"title":"发庐陵"},{"title":"铁柱观"},{"title":"舟次生米值风作"},{"title":"大孤山"},{"title":"赠知训上人"},{"title":"寄李知章"},{"title":"赠善懽禅师"},{"title":"送哲公禅老二首  其一"},{"title":"送哲公禅老二首  其二"},{"title":"次韵酬萧器之朝奉"},{"title":"次韵和贾仲武同诸公游狼山"},{"title":"再和贾仲武游狼山"},{"title":"赠雪峰长老守超"},{"title":"和仲武苦雨见寄"},{"title":"晚晴"},{"title":"赠黄成伯仇览"},{"title":"有诏遣移局实录院因成古诗奉别同舍学士诸公聊佐一笑"},{"title":"送李尧咨赴官山阳"},{"title":"送陈师益还建安"},{"title":"送曾灵永赴举"},{"title":"送新淦余宰虞卿"},{"title":"留题王公谟"},{"title":"赠王隠居适中"},{"title":"送元举宫苑秀州钤辖"},{"title":"再继权之严韵二首  其一"},{"title":"再继权之严韵二首  其二"},{"title":"送贯之县丞解官还寿春"},{"title":"次韵和彭道原元夕"},{"title":"书新兴罗汉室"},{"title":"次韵林锡远食蜂儿之句"},{"title":"题远上人休老庵"},{"title":"酒家逢徐逸人"},{"title":"志雁"},{"title":"海门故城"},{"title":"夜饮留李圣咨法曹走笔"},{"title":"我行"},{"title":"雷塘"},{"title":"依师小轩独酌"},{"title":"早发临川经回龙寺少刻因观李供奉壁画须菩提"},{"title":"留题疏山白云禅院因呈长老秀公"},{"title":"过昆阳城"},{"title":"鄱阳湖四十韵"},{"title":"蒋沙庄居十首  其一"},{"title":"蒋沙庄居十首  其二"},{"title":"蒋沙庄居十首  其三"},{"title":"蒋沙庄居十首  其四"},{"title":"蒋沙庄居十首  其五"},{"title":"蒋沙庄居十首  其六"},{"title":"蒋沙庄居十首  其七"},{"title":"蒋沙庄居十首  其八"},{"title":"蒋沙庄居十首  其九"},{"title":"蒋沙庄居十首  其一○"},{"title":"莆田杂诗二十首  其一"},{"title":"莆田杂诗二十首  其二"},{"title":"莆田杂诗二十首  其三"},{"title":"莆田杂诗二十首  其四"},{"title":"莆田杂诗二十首  其五"},{"title":"莆田杂诗二十首  其六"},{"title":"莆田杂诗二十首  其七"},{"title":"莆田杂诗二十首  其八"},{"title":"莆田杂诗二十首  其九"},{"title":"莆田杂诗二十首  其一○"},{"title":"莆田杂诗二十首  其一一"},{"title":"莆田杂诗二十首  其一二"},{"title":"莆田杂诗二十首  其一三"},{"title":"莆田杂诗二十首  其一四"},{"title":"莆田杂诗二十首  其一五"},{"title":"莆田杂诗二十首  其一六"},{"title":"莆田杂诗二十首  其一七"},{"title":"莆田杂诗二十首  其一八"},{"title":"莆田杂诗二十首  其一九"},{"title":"莆田杂诗二十首  其二○"},{"title":"早发赴蒙县二首  其一"},{"title":"早发赴蒙县二首  其二"},{"title":"赠谢民师"},{"title":"临江"},{"title":"赠李子从三十韵"},{"title":"伤段谦叔失意二十八韵"},{"title":"伤蔡文仲秋闱失意四十韵"},{"title":"伤友人潘镇之失意七十韵"},{"title":"题仰山二十韵"},{"title":"览唐元成诗因而有赠"},{"title":"春日舟中即事"},{"title":"读汪都讲邵宫教拟试赋三十韵"},{"title":"次韵奉酬邵美中奉议示同舍"},{"title":"览邵美中拟试赋出诗三十韵纪之邵有诗谢复次其韵"},{"title":"试院次韵奉酬赵达夫记室惜春之什  其一"},{"title":"试院次韵奉酬赵达夫记室惜春之什  其二"},{"title":"次韵酬朱充仁示同舍"},{"title":"张寿翁朝散有诗纪同舍名衔录次其韵"},{"title":"贡院奏号奉呈同舍诸公"},{"title":"晋之太博同舍常怆六世外祖郑氏苗裔中绝曩访得丘墓所在岁时享祀不辍乡里化之因有诗纪其事谋弇属和云"},{"title":"次韵和汪道济都讲惜惜吟"},{"title":"题福州黄蘗山确禅师息老堂"},{"title":"送林锡远帐勾罢官北引二首  其一"},{"title":"送林锡远帐勾罢官北引二首  其二"},{"title":"招季山还家"},{"title":"早发襄邑"},{"title":"夜泊建溪丰乐驿前三首  其一"},{"title":"夜泊建溪丰乐驿前三首  其二"},{"title":"夜泊建溪丰乐驿前三首  其三"},{"title":"赠邑宰詹志行长官"},{"title":"清真观步翠阁"},{"title":"清真观清轩"},{"title":"清真观斋轩"},{"title":"月波楼"},{"title":"贺氏怡轩"},{"title":"建德县作"},{"title":"新开湖诗  其一"},{"title":"新开湖诗  其二"},{"title":"送廷允决曹解官舟行赴阙    其一"},{"title":"送廷允决曹解官舟行赴阙    其二"},{"title":"次韵酬"},{"title":"次韵表民偶作"},{"title":"赠致政曾宣德十二韵"},{"title":"上金陵黄尚书安中二首  其一"},{"title":"上金陵黄尚书安中二首  其二"},{"title":"和安中东楼会饮"},{"title":"和安中铁柱留题"},{"title":"王公济四美楼"},{"title":"王公济兰荄亭"},{"title":"李倅惠诗次元韵酬谢"},{"title":"再次韵和酬"},{"title":"九曲池"},{"title":"搘筇"},{"title":"和重阳感怀"},{"title":"次韵酬锡远孤坐有怀"},{"title":"次韵和刘次公以诗见赠"},{"title":"寄兜率悦禅师二首  其一"},{"title":"寄兜率悦禅师二首  其二"},{"title":"次韵酬何伯修见贻"},{"title":"次韵酬何伯修"},{"title":"次韵酬谭履常送致政徐朝奉"},{"title":"王适中渝饮约以诗招之"},{"title":"送致政吴通直"},{"title":"谢何舜庸见借画舫还乡"},{"title":"次韵奉酬何舜庸寄酒"},{"title":"赠致政李元古二首  其一"},{"title":"赠致政李元古二首  其二"},{"title":"赠吴伯玉二首  其一"},{"title":"赠吴伯玉二首  其二"},{"title":"罗汉系南长老"},{"title":"送螺川张太守二首  其一"},{"title":"送螺川张太守二首  其二"},{"title":"和吴伯玉九日同会"},{"title":"次韵酬张商佐"},{"title":"清凉法和禅师"},{"title":"陪王纯父燕历阳连云观"},{"title":"江馆三首  其一"},{"title":"江馆三首  其二"},{"title":"江馆三首  其三"},{"title":"赠高邮尉郭奉世"},{"title":"灵鹫寺"},{"title":"光相洞"},{"title":"自竹岩至杉溪"},{"title":"送狄太守清明日燕莆田共乐亭三首  其一"},{"title":"送狄太守清明日燕莆田共乐亭三首  其二"},{"title":"送狄太守清明日燕莆田共乐亭三首  其三"},{"title":"宿泗洲院"},{"title":"建州试院次韵和林原叔监试"},{"title":"出试院次韵和酬郑通直二首  其一"},{"title":"出试院次韵和酬郑通直二首  其二"},{"title":"芝山"},{"title":"澄心亭"},{"title":"赠饶倅陈伯模朝奉二首郡事  其一"},{"title":"赠饶倅陈伯模朝奉二首郡事  其二"},{"title":"次韵陈伯模见赠之什"},{"title":"白鹭亭逢胡仙尉晋侯二首  其一"},{"title":"白鹭亭逢胡仙尉晋侯二首  其二"},{"title":"过合肥会黄天倪"},{"title":"上王提刑二首  其一"},{"title":"上王提刑二首  其二"},{"title":"赠致政刘大夫"},{"title":"赠连州致政蔡宣德"},{"title":"赠致政曾宣德"},{"title":"送友人赴省"},{"title":"送友人赴省二首  其一"},{"title":"送友人赴省二首  其二"},{"title":"冬日呈郭明远二首  其一"},{"title":"冬日呈郭明远二首  其二"},{"title":"春日送签判阳承议"},{"title":"春日送林推官"},{"title":"赠柳秀才三首  其一"},{"title":"赠柳秀才三首  其二"},{"title":"赠柳秀才三首  其三"},{"title":"题莲花市客肆壁二首  其一"},{"title":"题莲花市客肆壁二首  其二"},{"title":"真阳阻水"},{"title":"春日舟中即事"},{"title":"春日舟中喜晴三首  其一"},{"title":"春日舟中喜晴三首  其二"},{"title":"春日舟中喜晴三首  其三"},{"title":"题清风亭"},{"title":"题韶州宣溪亭"},{"title":"题广州浴日亭"},{"title":"海山楼晚望"},{"title":"春日即事"},{"title":"舟中惊夏"},{"title":"观刘禹锡题湟川记"},{"title":"赠钱承务吟翁"},{"title":"题清漪亭"},{"title":"次韵谭令尹茅庵十咏  其一"},{"title":"次韵谭令尹茅庵十咏  其二"},{"title":"次韵谭令尹茅庵十咏  其三"},{"title":"次韵谭令尹茅庵十咏  其四"},{"title":"次韵谭令尹茅庵十咏  其五"},{"title":"次韵谭令尹茅庵十咏  其六"},{"title":"次韵谭令尹茅庵十咏  其七"},{"title":"次韵谭令尹茅庵十咏  其八"},{"title":"次韵谭令尹茅庵十咏  其九"},{"title":"次韵谭令尹茅庵十咏  其一○"},{"title":"辇下春怀十绝呈赵达夫  其一"},{"title":"辇下春怀十绝呈赵达夫  其二"},{"title":"辇下春怀十绝呈赵达夫  其三"},{"title":"辇下春怀十绝呈赵达夫  其四"},{"title":"辇下春怀十绝呈赵达夫  其五"},{"title":"辇下春怀十绝呈赵达夫  其六"},{"title":"辇下春怀十绝呈赵达夫  其七"},{"title":"辇下春怀十绝呈赵达夫  其八"},{"title":"辇下春怀十绝呈赵达夫  其九"},{"title":"辇下春怀十绝呈赵达夫  其一○"},{"title":"再用前韵酬达夫  其一"},{"title":"再用前韵酬达夫  其二"},{"title":"再用前韵酬达夫  其三"},{"title":"再用前韵酬达夫  其四"},{"title":"再用前韵酬达夫  其五"},{"title":"再用前韵酬达夫  其六"},{"title":"再用前韵酬达夫  其七"},{"title":"再用前韵酬达夫  其八"},{"title":"再用前韵酬达夫  其九"},{"title":"再用前韵酬达夫  其一○"},{"title":"三用前韵酬达夫  其一"},{"title":"三用前韵酬达夫  其二"},{"title":"三用前韵酬达夫  其三"},{"title":"三用前韵酬达夫  其四"},{"title":"三用前韵酬达夫  其五"},{"title":"三用前韵酬达夫  其六"},{"title":"三用前韵酬达夫  其七"},{"title":"三用前韵酬达夫  其八"},{"title":"三用前韵酬达夫  其九"},{"title":"三用前韵酬达夫  其一○"},{"title":"四用前韵酬达夫  其一"},{"title":"四用前韵酬达夫  其二"},{"title":"四用前韵酬达夫  其三"},{"title":"四用前韵酬达夫  其四"},{"title":"四用前韵酬达夫  其五"},{"title":"四用前韵酬达夫  其六"},{"title":"四用前韵酬达夫  其七"},{"title":"四用前韵酬达夫  其八"},{"title":"四用前韵酬达夫  其九"},{"title":"四用前韵酬达夫  其一○"},{"title":"题建州富沙门楼安济桥十绝呈太守黄彦发 富沙门楼五绝 其一"},{"title":"题建州富沙门楼安济桥十绝呈太守黄彦发 富沙门楼五绝 其二"},{"title":"题建州富沙门楼安济桥十绝呈太守黄彦发 富沙门楼五绝 其三"},{"title":"题建州富沙门楼安济桥十绝呈太守黄彦发 富沙门楼五绝 其四"},{"title":"题建州富沙门楼安济桥十绝呈太守黄彦发 富沙门楼五绝 其五"},{"title":"题建州富沙门楼安济桥十绝呈太守黄彦发 安济桥五绝 其一"},{"title":"题建州富沙门楼安济桥十绝呈太守黄彦发 安济桥五绝 其二"},{"title":"题建州富沙门楼安济桥十绝呈太守黄彦发 安济桥五绝 其三"},{"title":"题建州富沙门楼安济桥十绝呈太守黄彦发 安济桥五绝 其四"},{"title":"题建州富沙门楼安济桥十绝呈太守黄彦发 安济桥五绝 其五"},{"title":"送曾道者归玉笥旧隠二首  其一"},{"title":"送曾道者归玉笥旧隠二首  其二"},{"title":"道旁见牛车因成二绝  其一"},{"title":"道旁见牛车因成二绝  其二"},{"title":"送李德素罢官归舒城三首  其一"},{"title":"送李德素罢官归舒城三首  其二"},{"title":"送李德素罢官归舒城三首  其三"},{"title":"和知府龙图黄安中浅沙马跑二泉二首  其一"},{"title":"和知府龙图黄安中浅沙马跑二泉二首  其二"},{"title":"和安中咏陈仲举徐孺子二首  其一"},{"title":"和安中咏陈仲举徐孺子二首  其二"},{"title":"和安中铁柱留题"},{"title":"和安中上蓝横泉井"},{"title":"陪彭安行双莲亭小酌三首  其一"},{"title":"陪彭安行双莲亭小酌三首  其二"},{"title":"陪彭安行双莲亭小酌三首  其三"},{"title":"留题神仙院三绝  其一"},{"title":"留题神仙院三绝  其二"},{"title":"留题神仙院三绝  其三"},{"title":"陪林明复功德院小轩对假山有成"},{"title":"试笔"},{"title":"西峰寺"},{"title":"赠庆恩禅师"},{"title":"高氏环翠楼二首  其一"},{"title":"高氏环翠楼二首  其二"},{"title":"莲华峰法云即事五首  其一"},{"title":"莲华峰法云即事五首  其二"},{"title":"莲华峰法云即事五首  其三"},{"title":"莲华峰法云即事五首  其四"},{"title":"莲华峰法云即事五首  其五"},{"title":"赵屯阻风书怀示黄成伯章子修二首  其一"},{"title":"赵屯阻风书怀示黄成伯章子修二首  其二"},{"title":"再次前韵  其一"},{"title":"再次前韵  其二"},{"title":"送徐择之秘校还雎阳二首  其一"},{"title":"送徐择之秘校还雎阳二首  其二"},{"title":"书国清寺清晓上人壁"},{"title":"和许亢秀才适轩三咏  其一"},{"title":"和许亢秀才适轩三咏  其二"},{"title":"和许亢秀才适轩三咏  其三"},{"title":"题屈原"},{"title":"题增城驻舟亭"},{"title":"题韶州韶石亭"},{"title":"泊韶州宣溪亭"},{"title":"题吉水南华寺  其一"},{"title":"题吉水南华寺  其二"},{"title":"龙云观稼"},{"title":"知府黄龙图生辰五首  其一"},{"title":"知府黄龙图生辰五首  其二"},{"title":"知府黄龙图生辰五首  其三"},{"title":"知府黄龙图生辰五首  其四"},{"title":"知府黄龙图生辰五首  其五"},{"title":"知府熊公待制生辰"},{"title":"上熊待制生辰二首  其一"},{"title":"上熊待制生辰二首  其二"},{"title":"王运判生辰二十韵"},{"title":"冬至上王丞相生日黄钟歌"},{"title":"狄大夫生辰二十韵"},{"title":"贺提刑生辰二十韵"},{"title":"哲宗皇帝挽词二首  其一"},{"title":"哲宗皇帝挽词二首  其二"},{"title":"大行皇太后挽词二首  其一"},{"title":"大行皇太后挽词二首  其二"},{"title":"追尊皇太后挽词二首  其一"},{"title":"追尊皇太后挽词二首  其二"},{"title":"何隠居挽词二首  其一"},{"title":"何隠居挽词二首  其二"},{"title":"欧阳升之挽辞"},{"title":"哭上蓝居晋禅师二首  其一"},{"title":"哭上蓝居晋禅师二首  其二"},{"title":"邓县君挽辞二首  其一"},{"title":"邓县君挽辞二首  其二"},{"title":"句"},{"title":"内家娇"},{"title":"安平乐慢 其六"},{"title":"佳人醉 元宵上太守"},{"title":"宝鼎现"},{"title":"金明春/金明池"},{"title":"洞仙歌"},{"title":"惜双双令/惜分飞"},{"title":"清平乐"},{"title":"送真藏主赴泐潭乾老会中"},{"title":"感寓二十首 其十"},{"title":"感寓二十首 其十三"},{"title":"感寓二十首 其十五"},{"title":"感寓二十首 其十六"},{"title":"感寓二十首 其十七"},{"title":"感寓二十首 其十八"},{"title":"感寓二十首 其十九"},{"title":"感寓二十首 其二十"},{"title":"秋日仪真即事十首 其十"},{"title":"赠善欢禅师"},{"title":"赠王隐居适中"},{"title":"莆田杂诗二十首 其十四"},{"title":"莆田杂诗二十首 其十五"},{"title":"莆田杂诗二十首 其十六"},{"title":"莆田杂诗二十首 其十七"},{"title":"莆田杂诗二十首 其十八"},{"title":"莆田杂诗二十首 其十九"},{"title":"题福州黄檗山确禅师息老堂"},{"title":"支筇"},{"title":"题建州富沙门楼安济桥十绝呈太守黄彦发 其三 富沙门楼五绝"},{"title":"题建州富沙门楼安济桥十绝呈太守黄彦发 其三 安济桥五绝"},{"title":"送曾道者归玉笥旧隐二首 其二"},{"title":"赵屯阻风书怀示黄成伯章子脩二首 其一"},{"title":"何隐居挽词二首 其一"},{"title":"何隐居挽词二首 其二"},{"title":"蒋沙庄居十首"},{"title":"莆田杂诗二十首"},{"title":"早发赴蒙县二首"},{"title":"大行皇太后挽词二首"},{"title":"追尊皇太后挽词二首"},{"title":"畏日三首"},{"title":"试院次韵奉酬赵达夫记室惜春之什"},{"title":"送林锡远帐勾罢官北引二首"},{"title":"夜泊建溪丰乐驿前三首"},{"title":"新开湖诗"},{"title":"送廷允决曹解官舟行赴阙"},{"title":"上金陵黄尚书安中二首"},{"title":"寄兜率悦禅师二首"},{"title":"赠致政李元古二首"},{"title":"赠吴伯玉二首"},{"title":"送螺川张太守二首"},{"title":"江馆三首"},{"title":"送狄太守清明日燕莆田共乐亭三首"},{"title":"白鹭亭逢胡仙尉晋侯二首"},{"title":"上王提刑二首"},{"title":"送友人赴省二首"},{"title":"冬日呈郭明远二首"},{"title":"赠柳秀才三首"},{"title":"题莲花市客肆壁二首"},{"title":"春日舟中喜晴三首"},{"title":"知府黄龙图生辰五首"},{"title":"上熊待制生辰二首"},{"title":"何隐居挽词二首"},{"title":"邓县君挽辞二首"},{"title":"次韵谭令尹茅庵十咏"},{"title":"辇下春怀十绝呈赵达夫"},{"title":"再用前韵酬达夫"},{"title":"三用前韵酬达夫"},{"title":"四用前韵酬达夫"},{"title":"题建州富沙门楼安济桥十绝呈太守黄彦发 富沙门楼五绝"},{"title":"题建州富沙门楼安济桥十绝呈太守黄彦发 安济桥五绝"},{"title":"送曾道者归玉笥旧隐二首"},{"title":"道旁见牛车因成二绝"},{"title":"送李德素罢官归舒城三首"},{"title":"和知府龙图黄安中浅沙马跑二泉二首"},{"title":"和安中咏陈仲举徐孺子二首"},{"title":"陪彭安行双莲亭小酌三首"},{"title":"留题神仙院三绝"},{"title":"高氏环翠楼二首"},{"title":"莲华峰法云即事五首"},{"title":"赵屯阻风书怀示黄成伯章子脩二首"},{"title":"再次前韵"},{"title":"送徐择之秘校还雎阳二首"},{"title":"和许亢秀才适轩三咏 小木"},{"title":"题吉水南华寺"},{"title":"哲宗皇帝挽词二首"},{"title":"送方绚解元赴试南宫用桂林一枝荆山片玉为韵八首"},{"title":"癸酉岁暮寿春道中五首"},{"title":"建阳县二首"},{"title":"宿法藏禅院二首"},{"title":"安成道中作六首"},{"title":"感寓二十首"},{"title":"秋日仪真即事十首"},{"title":"宿长山寺二首"},{"title":"送哲公禅老二首"},{"title":"再继权之严韵二首"},{"title":"哭上蓝居晋禅师二首"}]}