{"meta":{"id":"p216","name":"陈杰","dynasty":"song","category":"song","poemCount":354,"desc":"陈杰，字焘父，洪州丰城（今属江西）人。理宗淳祐十年（一二五○）进士，授赣州簿。历知江陵县，江南西路提点刑狱兼制置司参谋。据集中诗篇，知其还做过知州和短期朝官。宋亡，隠居东湖。有《自堂存稿》十三卷（《宋史艺文志补》），已佚。清四库馆臣据《永乐大典》辑为四卷。清同治《丰城县志》卷一六有传。　陈杰诗，以影印文渊阁《四库全书》本为底本。校以《豫章丛书》本（简称豫章本）、残本《永乐大典》等。新辑集外诗附于卷末。"},"bodyChunkSize":128,"poems":[{"title":"春日  其一"},{"title":"春日  其二"},{"title":"春日  其三"},{"title":"江永  其一"},{"title":"江永  其二"},{"title":"江永  其三"},{"title":"明月  其一"},{"title":"明月  其二"},{"title":"明月  其三"},{"title":"明月  其四"},{"title":"元和"},{"title":"清坐"},{"title":"送别"},{"title":"书徐经坂先志"},{"title":"曩从玉泉道人见寿亭侯印大可方二寸并解池龙骨一枚云侯所下讨者今从玄潭道人见旌阳令剑长不过五六寸云令留以镇水妖者皆微物远不可考道人请予赋剑因并及印以起兴焉"},{"title":"和山长胡端逸辞归"},{"title":"读史"},{"title":"望庐山"},{"title":"赠蔡俊民挟雷法兼眼科北行"},{"title":"陈梅境恩科晚遇由广而江帅幕留司索赋"},{"title":"苏东坡西山诗前后和者五十余篇暇日登览怆然有感于元祐绍圣之事僭亦用韵"},{"title":"淮南看雪歌"},{"title":"武冈向权叔家有陈魏祠堂合祀简斋鹤山惟两公世异事殊实难牵合诸公既极推引复征予言"},{"title":"重过西湖感事"},{"title":"寿康堂为吴氏题"},{"title":"维扬之役浩堂拨赐巨舟愿易小者"},{"title":"御风行送武夷道人谢叠山"},{"title":"权贵人"},{"title":"书孙州判澹翁再擒寇事迹"},{"title":"和张岳州雪夜弹琴"},{"title":"王仪仲名其读书之所曰松林愿印一言"},{"title":"尤物"},{"title":"送彭莱山谈星"},{"title":"题点易窗道人苏门遗啸"},{"title":"猛虎行"},{"title":"客谈矩山大资近事近诗及新相麻云欲浮海以安归走笔附讯"},{"title":"南山青"},{"title":"罗寿可再如旧都作归来窗以为亲悦劝之归者皆是予特下转语焉"},{"title":"林告院伯文送菊大如盖予谓惟黄繖两字可极形容遂赋"},{"title":"题王书史百鴈图"},{"title":"题寄傲轩"},{"title":"淮南听雨歌"},{"title":"金谷客"},{"title":"雪禁体"},{"title":"读苏武传"},{"title":"昭君怨"},{"title":"乙丑元日寿昌拜表"},{"title":"天基节特晴"},{"title":"寿昌元夕建醮"},{"title":"苏湖道间"},{"title":"送张教授赴广阙"},{"title":"大享先玄酒"},{"title":"寄黄思梅就别祖德"},{"title":"冶城清谈"},{"title":"题濂溪画像"},{"title":"题思妇"},{"title":"大阃拨醅于园亭坐上文武各半恰西师捷至用同官韵"},{"title":"请代"},{"title":"江亭秋思"},{"title":"江亭小憩"},{"title":"荆州雪"},{"title":"宣檄随府初程得风"},{"title":"重宿城头驿"},{"title":"斗牛山登高"},{"title":"山村"},{"title":"景陵湖中宿人村"},{"title":"冬至摄献于郊"},{"title":"出郊"},{"title":"和叶宋英"},{"title":"东湖夜坐松间"},{"title":"送朱靖州"},{"title":"饯西北流寓士舟赴南省"},{"title":"冬晴散步"},{"title":"初出大江移泊别浦"},{"title":"归梦"},{"title":"孔明"},{"title":"仲宣楼"},{"title":"晓登吴山二首  其一"},{"title":"晓登吴山二首  其二"},{"title":"郊行小憩"},{"title":"送安常簿"},{"title":"天人"},{"title":"寓舍琼花一株盛开"},{"title":"送程楚翁归歙用其韵"},{"title":"酬西山龚学谕"},{"title":"追哭泉谷徐侍郎墓"},{"title":"为农"},{"title":"和后林寄以梦中不知天尽头之韵"},{"title":"出关和雷侍郎送行无魔不成佛观过始知仁之句"},{"title":"和陈别魁元吉"},{"title":"懋勋挽辞"},{"title":"理考挽词"},{"title":"黄茶陵死寇吴荆溪作碑祭文云斥彼懦夫提此英魄为赋诗以挽之"},{"title":"太上务德"},{"title":"春昼睡起"},{"title":"探梅"},{"title":"赠孙仙辈"},{"title":"和萧太秀中秋月言内事"},{"title":"客来"},{"title":"送客"},{"title":"挽洛阳李教授丧北归"},{"title":"醉乡"},{"title":"挽念斋陈郎中"},{"title":"挽云屋徐侍郎"},{"title":"登钟山憩定林"},{"title":"夜发吴城渡"},{"title":"熊校尉挟名画来淮得官辞归"},{"title":"讯给事徐尚书自除知制诰归"},{"title":"宿东林寺"},{"title":"江头闲行送去客"},{"title":"扬子桥送客浮湘"},{"title":"挽李司谏"},{"title":"吴真州屡交诗而不及见告去送别"},{"title":"清明日新霁"},{"title":"出郭晚回"},{"title":"还家父老见迓境上"},{"title":"郊行遇乡人"},{"title":"年华"},{"title":"移居戍将衙"},{"title":"过衢阻潦宿民家"},{"title":"富州花朝用诸老韵"},{"title":"送陈知录赴班改秩"},{"title":"挽刘实斋尚书"},{"title":"赠高眼相士"},{"title":"送七姪游学"},{"title":"元旦南郊庆成"},{"title":"天基节特晴"},{"title":"人日立春极寒"},{"title":"腊月中旬立春快雪遄晴"},{"title":"除日始雪遄霁"},{"title":"过小孤顺风纵帆瞬息数百里"},{"title":"狮子寨小港軃风"},{"title":"阃下忽动归兴"},{"title":"旧爱灵溪渡风物之美归途由浙而江即目成咏"},{"title":"岁晏大风"},{"title":"三朝书窗"},{"title":"得菊花绝黄"},{"title":"归舟发南浦"},{"title":"送淮漕洪监移节江东暂回天目"},{"title":"和邓中斋至日舟中七言"},{"title":"正月三日甲子题"},{"title":"寸禄"},{"title":"京口闲行逢李编校谓尝共蒱戏于长安酒家殊惘然也"},{"title":"赠艾校尉"},{"title":"宪使魏青崖惠拄杖坚多节而色尚黄惟额用白立秋后十日声诗"},{"title":"沙头点视城池"},{"title":"挽陶县令叔元"},{"title":"挽张提点自创玄都观归故山羽化"},{"title":"闻履斋丞相再论贬"},{"title":"黄孟博辞往鄂渚赠别"},{"title":"滕王阁"},{"title":"冬至前七日青崖分送新历"},{"title":"陪蜀士文昌醮"},{"title":"仲宣楼"},{"title":"和诸君野舟之作"},{"title":"寄题兴国倅厅湖山伟观楼"},{"title":"答龚帅干楚清"},{"title":"和大阃芍药䜩韵"},{"title":"端午命童采药"},{"title":"咏物"},{"title":"病起"},{"title":"寻苏云卿隠处"},{"title":"风沙"},{"title":"寄赠"},{"title":"诗客有叹不遇者作诗人傲以慰之"},{"title":"伯文觅鸡雏赋送"},{"title":"携碧香酒赏红白桃因观江涨"},{"title":"题王氏先垅寿松亭"},{"title":"徐子苍自金陵遣诗来用韵送鱼腊"},{"title":"守岁"},{"title":"上元果晴䜩南楼诗弈尽欢用韵"},{"title":"五日江亭即事"},{"title":"题菊乡亭"},{"title":"把茅"},{"title":"南楼登高"},{"title":"江天"},{"title":"出郊"},{"title":"予以甲寅冬过弋阳石桥戊辰正月重过"},{"title":"和陈郎中时举清夜不寐"},{"title":"恶讲义不逊者"},{"title":"用同官南楼韵尾联以慰李倅子发"},{"title":"又登南楼"},{"title":"扬州城楼"},{"title":"索隠张君风鉴兼人未尝衣帛食肉自谓数短故勉之归就肆焉"},{"title":"小惠"},{"title":"泛西湖"},{"title":"和韵归赵宗圣诗卷"},{"title":"和韵归张通父诗卷"},{"title":"天命"},{"title":"武宁道间遇故旧于负贩中"},{"title":"感兴"},{"title":"和雷侍郎贺雪赐燕"},{"title":"空第"},{"title":"除夕"},{"title":"立春久渴雨大阃正月八日祷遄应"},{"title":"赠张慈宝五行精到奇中"},{"title":"即事二首  其一"},{"title":"即事二首  其二"},{"title":"感怀"},{"title":"十二月二十六日蔡叔庸至剪烛听雨"},{"title":"元宵"},{"title":"挽雷尚书丧归二首  其一"},{"title":"挽雷尚书丧归二首  其二"},{"title":"挽龚竹卿"},{"title":"挽黄思梅"},{"title":"挽范安仲死寇"},{"title":"和林一父自温陵寄诗由信上再忤时贵归本贯"},{"title":"和伯文送丁校尉往维扬伯文尝教之避祸不从"},{"title":"和钦弟读予孙吴之作"},{"title":"和天民寄笔"},{"title":"和姚山长一甫"},{"title":"和王守城山"},{"title":"和敖教谕"},{"title":"和夏南麓绣斧曾驱当道狼及答尹存吾喻仁山携诗相过值出"},{"title":"和曾平山见贻蚤自温荣挹艳香韵"},{"title":"与节东归和同幕送行之作"},{"title":"胡端逸结庵于清江之草鞋甲岁晏言别始知犹有九袠母在敬和韵"},{"title":"永穆陵复土随龙除官甚盛"},{"title":"徐祠曾碑久仆前山长胡端逸与士友共竖之邀予赋"},{"title":"沙头送客和伯文"},{"title":"食客"},{"title":"读邸报  其一"},{"title":"读邸报  其二"},{"title":"见邸报"},{"title":"扶惫效死清事久废奏院郭公应酉以旧翘馆客自杭来谈江上师溃及京城非才误著极为不平且辱惠书明日又为岭海之行勉强用韵"},{"title":"迓古心观相帅长沙"},{"title":"中斋生朝"},{"title":"山居"},{"title":"穷居"},{"title":"春风"},{"title":"浙江潮"},{"title":"试问"},{"title":"萱径携筇"},{"title":"菊畹秋香"},{"title":"昭君"},{"title":"琴窗夜雪"},{"title":"读书三首  其一"},{"title":"读书三首  其二"},{"title":"读书三首  其三"},{"title":"老米暮景"},{"title":"博弈观人二首  其一"},{"title":"博弈观人二首  其二"},{"title":"题子胥庙"},{"title":"题江山烟水图"},{"title":"述往二首  其一"},{"title":"述往二首  其二"},{"title":"题石泉渔歌"},{"title":"与伯文同作生朝林母在闽"},{"title":"赠雪篷相士"},{"title":"小桂二首  其一"},{"title":"小桂二首  其二"},{"title":"笃志斋前新竹"},{"title":"题和靖祠"},{"title":"贵要之客来"},{"title":"闻须溪坐午谢客用所寄绝句韵叶宋英先容"},{"title":"龙湾野店同军校举杯"},{"title":"和落梅"},{"title":"柴桑图"},{"title":"和雷侍郎省身湖上遇雪"},{"title":"题汤隽溪留远法师莲社图"},{"title":"题老杜巡簷索笑图"},{"title":"贾鹿泉屡约一出小诗代行十首  其一"},{"title":"贾鹿泉屡约一出小诗代行十首  其二"},{"title":"贾鹿泉屡约一出小诗代行十首  其三"},{"title":"贾鹿泉屡约一出小诗代行十首  其四"},{"title":"贾鹿泉屡约一出小诗代行十首  其五"},{"title":"贾鹿泉屡约一出小诗代行十首  其六"},{"title":"贾鹿泉屡约一出小诗代行十首  其七"},{"title":"贾鹿泉屡约一出小诗代行十首  其八"},{"title":"贾鹿泉屡约一出小诗代行十首  其九"},{"title":"贾鹿泉屡约一出小诗代行十首  其一○"},{"title":"送林一甫试浙漕二首  其一"},{"title":"送林一甫试浙漕二首  其二"},{"title":"伯文送海红柑及橄榄  其一"},{"title":"伯文送海红柑及橄榄  其二"},{"title":"灯夕解嘲和同官二首  其一"},{"title":"灯夕解嘲和同官二首  其二"},{"title":"春事"},{"title":"赠熊易课"},{"title":"红梅"},{"title":"古道"},{"title":"故人家"},{"title":"除夕对梅花烛花二首  其一"},{"title":"除夕对梅花烛花二首  其二"},{"title":"小春桃李俱花"},{"title":"赠玉壶相士"},{"title":"月窗相士"},{"title":"赠冰月相士"},{"title":"和叶宋英三绝句  其一"},{"title":"和叶宋英三绝句  其二"},{"title":"和叶宋英三绝句  其三"},{"title":"和张纯父霜月三首  其一"},{"title":"和张纯父霜月三首  其二"},{"title":"和张纯父霜月三首  其三"},{"title":"和州秋阳"},{"title":"和成修堂见寄吟稿韵二首  其一"},{"title":"和成修堂见寄吟稿韵二首  其二"},{"title":"和友人生香四和"},{"title":"破屋"},{"title":"挽周溪园国史三首  其一"},{"title":"挽周溪园国史三首  其二"},{"title":"挽周溪园国史三首  其三"},{"title":"劝农同幕皆预即事四绝  其一"},{"title":"劝农同幕皆预即事四绝  其二"},{"title":"劝农同幕皆预即事四绝  其三"},{"title":"劝农同幕皆预即事四绝  其四"},{"title":"见诸君感事之作"},{"title":"题李生烟江万里图"},{"title":"赠徐先辈星命课"},{"title":"闭门"},{"title":"东湖晚步洪恩桥海棠洞三首  其一"},{"title":"东湖晚步洪恩桥海棠洞三首  其二"},{"title":"东湖晚步洪恩桥海棠洞三首  其三"},{"title":"咏归晚步"},{"title":"书生旧梦二解皆因榜过作  其一"},{"title":"书生旧梦二解皆因榜过作  其二"},{"title":"和徐子苍扬州梦梅"},{"title":"寒梦"},{"title":"题驿壁"},{"title":"六朝"},{"title":"咏涂璋家屏风上题宣和壬寅季夏"},{"title":"咏史"},{"title":"题梅坛毛庆甫道士云悦楼"},{"title":"答李道士"},{"title":"题傅道士鹤鸣泉"},{"title":"酬别孙道人存心归上饶二首  其一"},{"title":"酬别孙道人存心归上饶二首  其二"},{"title":"和诸公琼花二首  其一"},{"title":"和诸公琼花二首  其二"},{"title":"题宣和御画芦禽"},{"title":"男竹枝歌"},{"title":"女竹枝歌"},{"title":"和彭教谕论诗"},{"title":"诵诗"},{"title":"无题  其一"},{"title":"无题  其二"},{"title":"无题  其三"},{"title":"至日拜赐"},{"title":"程簿能静袖诗来访次韵"},{"title":"东湖"},{"title":"西湖"},{"title":"小家住深村"},{"title":"送中斋过家入燕"},{"title":"充善堂为吴氏题"},{"title":"中兴事迹"},{"title":"送万平野余秋山被荐北行"},{"title":"题信州月岩"},{"title":"秋热抵信上一歌馆壁张芦雁寒林"},{"title":"大窖啮旃"},{"title":"先主"},{"title":"曹操"},{"title":"司马懿"},{"title":"登岳阳楼"},{"title":"阙题"}]}