{"meta":{"id":"p376","name":"李益","dynasty":"tang","category":"tang","poemCount":193,"desc":"李益，字君虞，姑臧人。大历四年登进士第，授郑县尉，久不调。益不得意，北游河朔，幽州刘济辟为从事，尝与济诗，有怨望语。宪宗时，召为秘书少监、集贤殿学士，自负才地，多所凌忽，为众不容。谏官举其幽州诗句，降居散秩。俄复用为秘书监，迁太子宾客、集贤学士、判院事，转右散骑常侍。太和初，以礼部尚书致仕卒。益长于歌诗，贞元末，与宗人李贺齐名，每作一篇，教坊乐人以赂求取，唱为供奉歌辞。其《征人歌》、《早行篇》，好事画为屏障。集一卷，今编诗二卷。"},"bodyChunkSize":128,"poems":[{"title":"横吹曲辞 紫骝马"},{"title":"相和歌辞 江南曲"},{"title":"相和歌辞 置酒行"},{"title":"相和歌辞 从军有苦乐行"},{"title":"相和歌辞 宫怨"},{"title":"杂曲歌辞 汉宫少年行"},{"title":"杂曲歌辞 轻薄篇"},{"title":"杂曲歌辞 游子吟"},{"title":"杂曲歌辞 古别离"},{"title":"从军有苦乐行"},{"title":"登长城"},{"title":"杂曲"},{"title":"送辽阳使还军"},{"title":"赋得早燕送别"},{"title":"秋晚溪中寄怀大理齐司直"},{"title":"溪中月下寄杨子尉封亮"},{"title":"春晚赋得余花落"},{"title":"闻亡友王七嘉禾寺得素琴"},{"title":"校书郎杨凝往年以古镜贶别今追赠以诗"},{"title":"置酒行"},{"title":"长社窦明府宅夜送王屋道士常究子"},{"title":"观回军三韵"},{"title":"华山南庙"},{"title":"喜邢校书远至对雨同赋远晚饭阮返五韵"},{"title":"城西竹园送裴佶王达"},{"title":"月下喜邢校书至自洛"},{"title":"北至太原"},{"title":"入华山访隐者经仙人石坛"},{"title":"罢镜"},{"title":"华阴东泉同张处士诣藏律师兼简县内同官因寄齐中书"},{"title":"答郭黄中孤云首章见赠"},{"title":"合源溪期张计不至"},{"title":"竹溪"},{"title":"送诸曁王主簿之任"},{"title":"罢秩后入华山采茯苓逢道者"},{"title":"自朔方还与郑式瞻崔称郑子周岑赞同会法云寺三门避暑"},{"title":"来从窦车骑行"},{"title":"夜发军中"},{"title":"将赴朔方早发汉武泉"},{"title":"城傍少年"},{"title":"游子吟"},{"title":"饮马歌"},{"title":"莲塘驿"},{"title":"五城道中"},{"title":"与王楚同登青龙寺上方"},{"title":"登夏州城观送行人赋得六州胡儿歌"},{"title":"从军夜次六胡北饮马磨劒石为祝殇辞"},{"title":"登天坛夜见海"},{"title":"大礼毕皇帝御丹凤门改元建中大赦"},{"title":"轻薄篇"},{"title":"野田行"},{"title":"古别离"},{"title":"效古促促曲为河上思妇作"},{"title":"汉宫少年行"},{"title":"竹窗闻风寄苗发司空曙"},{"title":"赋得垣衣"},{"title":"送人流贬"},{"title":"送人南归"},{"title":"水亭夜坐赋得晓雾"},{"title":"送常曾侍御使西蕃寄题西川"},{"title":"入南山至全师兰若"},{"title":"送韩将军还边"},{"title":"晚春卧病喜振上人见访"},{"title":"春行"},{"title":"洛阳河亭奉酬留守群公追送"},{"title":"寻纪道士偶会诸叟"},{"title":"同萧炼师宿太乙庙"},{"title":"送同落第者东归"},{"title":"送柳判官赴振武"},{"title":"述怀寄衡州令狐相公"},{"title":"喜入兰陵望紫阁峰呈宣上人"},{"title":"喜见外弟又言别"},{"title":"立春日宁州行营因赋朔风吹飞雪"},{"title":"献刘济"},{"title":"哭柏岩禅师"},{"title":"赴邠宁留别"},{"title":"紫骝马"},{"title":"夜上受降城闻笛"},{"title":"同崔邠登鹳雀楼"},{"title":"奉酬崔员外副使携琴宿使院见示"},{"title":"送贾校书东归寄振上人"},{"title":"过马嵬二首 一"},{"title":"过马嵬二首 二"},{"title":"盐州过胡儿饮马泉"},{"title":"宿冯翊夜雨赠主人"},{"title":"送襄阳李尚书"},{"title":"春日晋祠同声会集得疎字韵"},{"title":"再赴渭北使府留别"},{"title":"送归中丞使新罗册立吊祭"},{"title":"赋得路傍一株柳送邢校书赴延州使府"},{"title":"重赠邢校书"},{"title":"照镜"},{"title":"书院无历日以诗代书问路侍御六月大小"},{"title":"闻鸡赠主人"},{"title":"登白楼见白鸟席上命鹧鸪辞"},{"title":"石楼山见月"},{"title":"惜春伤同幕故人孟郎中兼呈去年看花友"},{"title":"嘉禾寺见亡友王七题壁"},{"title":"听唱赤白桃李花"},{"title":"江南词"},{"title":"赠内兄卢纶"},{"title":"答窦二曹长留酒还榼"},{"title":"答广宣供奉问兰陵居"},{"title":"乞宽禅师瘿山罍呈宣供奉"},{"title":"观骑射"},{"title":"幽州赋诗见意时佐刘幕"},{"title":"军次阳城烽舍北流泉"},{"title":"金吾子"},{"title":"山鹧鸪词"},{"title":"立秋前一日览镜"},{"title":"代人乞花"},{"title":"上洛桥"},{"title":"扬州怀古"},{"title":"水宿闻雁"},{"title":"扬州早雁"},{"title":"下楼"},{"title":"度破讷沙二首 一"},{"title":"度破讷沙二首 二"},{"title":"拂云堆"},{"title":"中桥北送穆质兄弟应制戏赠萧二策"},{"title":"九月十日雨中过张伯佳期柳镇未至以诗招之"},{"title":"汴河曲"},{"title":"塞下曲 一"},{"title":"塞下曲 二"},{"title":"塞下曲 三"},{"title":"塞下曲 四"},{"title":"夜上西城听梁州曲二首 一"},{"title":"夜上西城听梁州曲二首 二"},{"title":"暖川"},{"title":"过马嵬"},{"title":"答许五端公马上口号"},{"title":"牡丹"},{"title":"边思"},{"title":"奉和武相公春晓闻莺"},{"title":"送客还幽州"},{"title":"柳杨送客"},{"title":"从军北征"},{"title":"听晓角"},{"title":"宫怨"},{"title":"暮过回乐烽"},{"title":"奉和武相公郊居寓目"},{"title":"诣红楼院寻广宣不遇留题"},{"title":"回军行"},{"title":"邠宁春日"},{"title":"古瑟怨"},{"title":"夜宴观石将军舞"},{"title":"春夜闻笛"},{"title":"扬州送客"},{"title":"统汉峰下"},{"title":"避暑女冠"},{"title":"行舟"},{"title":"隋宫燕"},{"title":"送人归岳阳"},{"title":"上汝州郡楼"},{"title":"临滹沱见蕃使列名"},{"title":"写情"},{"title":"夜上受降城闻笛"},{"title":"赴渭北宿石泉驿南望黄堆烽"},{"title":"逢归信偶寄"},{"title":"赠毛仙翁"},{"title":"长干行"},{"title":"和丘员外题湛长史旧居"},{"title":"送客归振武"},{"title":"府试古镜"},{"title":"赠宣大师"},{"title":"汉宫词"},{"title":"江南曲"},{"title":"宿石邑山中"},{"title":"寄赠衡州杨使君"},{"title":"途中寄李二"},{"title":"寄许炼师"},{"title":"失题"},{"title":"塞下曲"},{"title":"上黄堆烽"},{"title":"句"},{"title":"杂曲歌辞 鹧鸪词"},{"title":"宣上人病中相寻联句"},{"title":"八月十五夜宣上人独游安国寺山庭院步人迟明将至因话昨宵乘兴联句"},{"title":"重阳夜集兰陵居与宣上人联句"},{"title":"与宣供奉携瘿尊归杏溪园联句"},{"title":"兰陵僻居联句"},{"title":"天津桥南山中各题一句"},{"title":"红楼下联句"},{"title":"赋应门照绿苔"},{"title":"游栖岩寺"},{"title":"杂曲歌辞 其一 祓禊曲"},{"title":"同萧鍊师宿太乙庙"},{"title":"春日晋祠同声会集得疏字韵"},{"title":"从军夜次六胡北饮马磨剑石为祝殇辞"},{"title":"春晚赋得馀花落"},{"title":"过马嵬二首"},{"title":"度破讷沙二首"},{"title":"夜上西城听梁州曲二首"}]}