{"meta":{"id":"p415","name":"范浚","dynasty":"song","category":"song","poemCount":202,"desc":"范浚（一一○二～一一五○），字茂明，兰谿（今属浙江）人。学者称香溪先生。高宗绍兴元年（一一三一）举贤良方正，不起，闭门讲学。朱熹以浚所撰《心箴》全载入《孟子集注》，由是知名。二十年卒，年四十九。遗文由其姪端臣编为《香溪先生文集》二十二卷。事见本集吴师道后序、明童品《香溪先生传》。　范浚诗，以《四部丛刊》影印瞿氏铁琴铜剑楼藏明万历十三年刊本为底本，校以影印文渊阁《四库全书》本（简称四库本）。"},"bodyChunkSize":128,"poems":[{"title":"杂兴五首  其一"},{"title":"杂兴五首  其二"},{"title":"杂兴五首  其三"},{"title":"杂兴五首  其四"},{"title":"杂兴五首  其五"},{"title":"遣兴五首  其一"},{"title":"遣兴五首  其二"},{"title":"遣兴五首  其三"},{"title":"遣兴五首  其四"},{"title":"遣兴五首  其五"},{"title":"题八马图"},{"title":"寄谢潘舍人赠乌纱帽"},{"title":"游兰谿灵洞"},{"title":"题弟茂通斗斋"},{"title":"寄题钱伯茂致政奉议遥碧轩"},{"title":"寄题何元晋亦乐堂"},{"title":"送春曲"},{"title":"春融融效李长吉体"},{"title":"同姪伯通端杲效卢仝体"},{"title":"同弟茂通效温飞卿体"},{"title":"送乔民瞻倅武昌"},{"title":"送徐履之倅南昌"},{"title":"六笑"},{"title":"读杨子云传"},{"title":"读王建射虎行"},{"title":"冬夜有感"},{"title":"送兄茂瞻机宜之官广东"},{"title":"赠青城道人"},{"title":"理喻  其一"},{"title":"理喻  其二"},{"title":"杂兴四首  其一"},{"title":"杂兴四首  其二"},{"title":"杂兴四首  其三"},{"title":"杂兴四首  其四"},{"title":"听琴"},{"title":"寓居宝惠寺喜晴登山"},{"title":"次韵姪端方过予偕行南村玩月"},{"title":"送四兄茂安之任永嘉"},{"title":"次韵姪端臣雨晴出郊"},{"title":"送袁上人还铜山"},{"title":"寄题余姚严公堂"},{"title":"叹旱"},{"title":"戏赠蜀僧清鉴"},{"title":"读长门赋"},{"title":"上李舍人"},{"title":"送徐彦思倅建安"},{"title":"拟李太白笑矣乎"},{"title":"龙游吴宰因劝农过寓居  其一"},{"title":"龙游吴宰因劝农过寓居  其二"},{"title":"龙游吴宰因劝农过寓居  其三"},{"title":"龙游吴宰因劝农过寓居  其四"},{"title":"龙游王丞相过寓居  其一"},{"title":"龙游王丞相过寓居  其二"},{"title":"龙游王丞相过寓居  其三"},{"title":"四月一日偶成三绝句奉勉诸友  其一"},{"title":"四月一日偶成三绝句奉勉诸友  其二"},{"title":"四月一日偶成三绝句奉勉诸友  其三"},{"title":"送李国佐还三衢"},{"title":"送赵安伯县丞之任婺源"},{"title":"凌霄花"},{"title":"题武康唐伯南扫月轩"},{"title":"寄题郑亨仲可友亭"},{"title":"四睡次三兄茂载韵  其一"},{"title":"四睡次三兄茂载韵  其二"},{"title":"四睡次三兄茂载韵  其三"},{"title":"四睡次三兄茂载韵  其四"},{"title":"暮春病起绝句二首  其一"},{"title":"暮春病起绝句二首  其二"},{"title":"浦江华藏寺如胜上人欲募施者开田佐僧供以长老皎公书来求予诗作二十韵奉勉"},{"title":"郊行探春得梅林攀玩为乐因成诗示偕行"},{"title":"次韵楼仲辉郎中游天王寺登城晚归三绝句  其一"},{"title":"次韵楼仲辉郎中游天王寺登城晚归三绝句  其二"},{"title":"次韵楼仲辉郎中游天王寺登城晚归三绝句  其三"},{"title":"次韵姪端臣感兴"},{"title":"次韵婺守林懿成检正游赤松绝句四首  其一"},{"title":"次韵婺守林懿成检正游赤松绝句四首  其二"},{"title":"次韵婺守林懿成检正游赤松绝句四首  其三"},{"title":"次韵婺守林懿成检正游赤松绝句四首  其四"},{"title":"次韵姪端臣喜雨"},{"title":"送别姚令声删定还诸暨"},{"title":"示姪"},{"title":"示友"},{"title":"送张子经抚干还临安幕"},{"title":"送叶彦益县丞之任江宁"},{"title":"对酒分和杜诗"},{"title":"游赤松观"},{"title":"次韵弟茂通立春四首  其一"},{"title":"次韵弟茂通立春四首  其二"},{"title":"次韵弟茂通立春四首  其三"},{"title":"次韵弟茂通立春四首  其四"},{"title":"赠清鉴上人"},{"title":"寄题赵叔才秀芝堂"},{"title":"苦寒行"},{"title":"凄凉行"},{"title":"三月廿六日夜同姪端臣端杲观异书效李长吉体"},{"title":"四月十六日同弟姪效李长吉体分韵得首字"},{"title":"偶作二首  其一"},{"title":"偶作二首  其二"},{"title":"狂泉"},{"title":"次韵六兄茂永论有无之作"},{"title":"己巳十二月廿九日同姪端臣端杲观王右军帖并晋书以白藕荐酒成诗"},{"title":"池上晚酌"},{"title":"题双清堂"},{"title":"陶潜咏"},{"title":"次韵六兄茂永首夏新晴"},{"title":"题四兄茂安藏春园"},{"title":"题四兄茂安秀野亭"},{"title":"次韵弟茂通晚晴"},{"title":"岁暮喜晴"},{"title":"初冬郊行"},{"title":"游严州景德寺"},{"title":"雨后出郊二首  其一"},{"title":"雨后出郊二首  其二"},{"title":"登富阳观山亭"},{"title":"张子经示所得后湖居士诗及书札想见其人寄意短韵"},{"title":"次韵姪端臣晚行南溪"},{"title":"课畦丁灌园"},{"title":"春望二首  其一"},{"title":"春望二首  其二"},{"title":"读孔北海传"},{"title":"春雪晚晴出西村"},{"title":"送周西美主簿之任祁门"},{"title":"次韵陈叔永山居二首  其一"},{"title":"次韵陈叔永山居二首  其二"},{"title":"西园"},{"title":"戏效白傅体送姚删定"},{"title":"避盗泊舟武康远光亭下与同行分和杜工部诗伤秋及宿江边阁二首  其一"},{"title":"避盗泊舟武康远光亭下与同行分和杜工部诗伤秋及宿江边阁二首  其二"},{"title":"游南山晚归二首  其一"},{"title":"游南山晚归二首  其二"},{"title":"贺长兄茂宽赐绯"},{"title":"李修撰哀挽二首  其一"},{"title":"李修撰哀挽二首  其二"},{"title":"冬日行兰谿道中六言二首  其一"},{"title":"冬日行兰谿道中六言二首  其二"},{"title":"忘言示曾仲思"},{"title":"春日行兰谿道中六言"},{"title":"次韵弟茂通郊行见梅"},{"title":"次韵姪端臣七夕"},{"title":"赠光上人"},{"title":"张生夜载酒相过"},{"title":"幽居"},{"title":"寓龙丘次韵六兄茂永见寄"},{"title":"姪端旻示游浦江花藏寺诗且道皎老相问意因次韵并烦为简皎公禅师"},{"title":"次韵三兄茂载偶成二首  其一"},{"title":"次韵三兄茂载偶成二首  其二"},{"title":"送欧丈朝请赴阙"},{"title":"春饮分章字韵"},{"title":"次韵富修仲见赠二首  其一"},{"title":"次韵富修仲见赠二首  其二"},{"title":"过严州乌龙岭"},{"title":"次韵翁承之见寄二首  其一"},{"title":"次韵翁承之见寄二首  其二"},{"title":"怀曹宗臣并寄"},{"title":"次韵姪伯通岁暮即事"},{"title":"悼致政楼少师  其一"},{"title":"悼致政楼少师  其二"},{"title":"寓居兰谿地湿卧病"},{"title":"次韵姪端臣同游藏春园"},{"title":"咏东山"},{"title":"次韵姪端方喜雪"},{"title":"送王大声"},{"title":"三兄茂载燕兄弟预者六友宜尽觞咏之乐长兄茂宽有诗因次其韵"},{"title":"游兰溪灵洞"},{"title":"同侄伯通端杲效卢仝体"},{"title":"次韵侄端方过予偕行南村玩月"},{"title":"寄题馀姚严公堂"},{"title":"四睡次三兄茂载韵 其一 春"},{"title":"四睡次三兄茂载韵 其二 夏"},{"title":"四睡次三兄茂载韵 其四 冬"},{"title":"次韵侄端臣感兴"},{"title":"次韵侄端臣喜雨"},{"title":"示侄"},{"title":"三月廿六日夜同侄端臣端杲观异书效李长吉体"},{"title":"次韵侄端臣晚行南溪"},{"title":"次韵侄端臣七夕"},{"title":"次韵侄伯通岁暮即事"},{"title":"寓居兰溪地湿卧病"},{"title":"次韵侄端方喜雪"},{"title":"杂兴五首"},{"title":"雨后出郊二首"},{"title":"春望二首"},{"title":"游南山晚归二首"},{"title":"李修撰哀挽二首"},{"title":"次韵富修仲见赠二首"},{"title":"次韵三兄茂载偶成二首"},{"title":"次韵翁承之见寄二首"},{"title":"悼致政楼少师"},{"title":"龙游吴宰因劝农过寓居"},{"title":"龙游王丞相过寓居"},{"title":"四月一日偶成三绝句奉勉诸友"},{"title":"四睡次三兄茂载韵 春"},{"title":"暮春病起绝句二首"},{"title":"次韵楼仲辉郎中游天王寺登城晚归三绝句"},{"title":"次韵婺守林懿成检正游赤松绝句四首"},{"title":"次韵弟茂通立春四首"},{"title":"遣兴五首"},{"title":"理喻"},{"title":"杂兴四首"},{"title":"偶作二首"},{"title":"次韵陈叔永山居二首"},{"title":"冬日行兰溪道中六言二首"}]}