{"meta":{"id":"p448","name":"陈允平","dynasty":"song","category":"song","poemCount":364,"desc":"陈允平，字衡仲，又字君衡，号西麓，鄞县（今浙江宁波）人。试上舍不遇，遂放情山水，往来吴淞淮泗间。恭宗德祐时，授沿海制置司参议官（《宋元学案》卷二五《参议陈西麓允平先生》）。宋亡，以人才征至元大都。不受官，放还。事见《两宋名贤小集》卷三一五《西麓诗稿》卷首、《宋诗略》卷一五。　陈允平诗，以汲古阁影宋抄《南宋六十家小集·西麓诗稿》为底本，校以《两宋名贤小集》（简称名贤集）。新辑集外诗编为第二卷。"},"bodyChunkSize":128,"poems":[{"title":"秦鸾曲"},{"title":"登吴山"},{"title":"明皇按乐图"},{"title":"鄂王墓"},{"title":"贺伯父大资休致"},{"title":"送中上人游天台"},{"title":"寄王尊师"},{"title":"过田家"},{"title":"秋暮登太白"},{"title":"雪"},{"title":"观弈象棋"},{"title":"香奁体"},{"title":"侍谢立斋小酌湖楼"},{"title":"题李丹壶壁"},{"title":"谒乌龙庙"},{"title":"即事"},{"title":"春词"},{"title":"江南谣"},{"title":"叹镜辞"},{"title":"登招宝山"},{"title":"秋夜游东墅"},{"title":"春游曲"},{"title":"春闺怨"},{"title":"野人家"},{"title":"游阳明洞天"},{"title":"哭楼梅麓"},{"title":"宫词"},{"title":"无题"},{"title":"题胡月山吟屋"},{"title":"有所思"},{"title":"观猿"},{"title":"失鹤"},{"title":"宿大慈山悟真观"},{"title":"寄翁宾旸"},{"title":"下第怀楼寿朋"},{"title":"别何橘潭"},{"title":"有感"},{"title":"暮春"},{"title":"终日"},{"title":"过钓台作"},{"title":"春闺"},{"title":"倚楼"},{"title":"严陵郡舍"},{"title":"西兴"},{"title":"曹娥庙"},{"title":"梁湖道上"},{"title":"闺情"},{"title":"梅梁堰"},{"title":"虎丘即事"},{"title":"青龙渡头"},{"title":"仲冬南楼野望"},{"title":"夜泊"},{"title":"梨花"},{"title":"赋林景参梅屿"},{"title":"怀潘鄮屋"},{"title":"吴江道上"},{"title":"登西楼怀汤损之"},{"title":"吴山雪霁"},{"title":"后土庙"},{"title":"湖上"},{"title":"西湖暮春"},{"title":"山房"},{"title":"马塍道上"},{"title":"游仙曲"},{"title":"戍妇"},{"title":"过姚秋江钓矶"},{"title":"己酉秋留鹤江有感"},{"title":"经冯将军墓"},{"title":"江村"},{"title":"江馆野望"},{"title":"暮秋游虎丘"},{"title":"小楼"},{"title":"侍赵别驾宴寿乐堂"},{"title":"留鹤江有感"},{"title":"送吴松溪过淮"},{"title":"送赵知县归天台"},{"title":"姑苏馆"},{"title":"云间洞天"},{"title":"采桑行"},{"title":"对烛"},{"title":"春晓"},{"title":"侍赵开府夜宴"},{"title":"雷峰少憩"},{"title":"钱塘旅舍"},{"title":"避暑"},{"title":"山中吟"},{"title":"山中吟  其一"},{"title":"山中吟  其二"},{"title":"山中吟  其三"},{"title":"山中吟  其四"},{"title":"山中吟  其五"},{"title":"山中吟  其六"},{"title":"山中吟  其七"},{"title":"山中吟  其八"},{"title":"山中吟  其九"},{"title":"山中吟  其一○"},{"title":"无题  其一"},{"title":"无题  其二"},{"title":"人日即事"},{"title":"客中怀友"},{"title":"忆诸姪"},{"title":"赠杜郎中"},{"title":"赠佛光法师"},{"title":"赠新罗僧"},{"title":"赠雪窦"},{"title":"赠律师"},{"title":"赠讷行人"},{"title":"赠东皋恭行人"},{"title":"赠罗知宫"},{"title":"赠明道者"},{"title":"赠杨子中"},{"title":"寄模上人"},{"title":"寄赵庆御"},{"title":"寄晚浦张观使"},{"title":"酬同志"},{"title":"茅苇"},{"title":"先天李姆庙"},{"title":"宛陵道院"},{"title":"伍炼士松隠居"},{"title":"林道士故庐"},{"title":"许宣平祠"},{"title":"郭西文孝庙"},{"title":"聚景园"},{"title":"补陀山"},{"title":"四明洞天"},{"title":"盘陀"},{"title":"江阔"},{"title":"淮西"},{"title":"雪窦"},{"title":"春塘"},{"title":"钱塘八月潮"},{"title":"芝山"},{"title":"堤上柳"},{"title":"城西杨梅"},{"title":"僧房薜荔"},{"title":"归燕"},{"title":"宿鹭"},{"title":"猿"},{"title":"故宫"},{"title":"长门曲"},{"title":"多景楼"},{"title":"清风阁"},{"title":"冷泉亭"},{"title":"姑苏台"},{"title":"春闺"},{"title":"绿琐"},{"title":"台上"},{"title":"丰乐楼初成"},{"title":"竹枝曲"},{"title":"一寸金"},{"title":"一落索 其二"},{"title":"一落索 其一"},{"title":"丁香结"},{"title":"八声甘州 代蔡泉使寿丁丞相"},{"title":"八声甘州 曲院风荷"},{"title":"八声甘州 寿蔡泉宪"},{"title":"八宝妆 秋宵有感"},{"title":"三犯渡江云/渡江云 旧平声，今改入声，为竹友谢少保寿"},{"title":"大犯 元夕寓京"},{"title":"大酺"},{"title":"小重山"},{"title":"丑奴儿/采桑子"},{"title":"丹凤吟"},{"title":"六么令"},{"title":"六丑"},{"title":"凤来朝"},{"title":"少年游 寿云谷谢右司"},{"title":"少年游 其二"},{"title":"少年游 其一"},{"title":"少年游 其四"},{"title":"少年游 其三"},{"title":"忆旧游"},{"title":"月上海棠"},{"title":"月中行/月宫春"},{"title":"木兰花慢 赋牡丹"},{"title":"木兰花慢"},{"title":"木兰花慢 丙辰寿叶制相"},{"title":"木兰花/玉楼春"},{"title":"水龙吟 奉川化凤花"},{"title":"水龙吟"},{"title":"风入松 寿恕齐谢待制"},{"title":"风流子 其二"},{"title":"风流子 其一"},{"title":"兰陵王 辛酉代寿壑翁丞相母夫人"},{"title":"兰陵王"},{"title":"四园竹"},{"title":"氐州第一"},{"title":"永遇乐 旧上声韵，今移入平声"},{"title":"汉宫春 其一 寿乡帅范尚书。郡有苍云堂，因古柏得名"},{"title":"汉宫春 芍药"},{"title":"汉宫春 其二 庚午岁寿谷翁保相"},{"title":"玉楼春 其三"},{"title":"玉楼春 其一"},{"title":"玉楼春 其二"},{"title":"玉楼春 其五"},{"title":"玉楼春 其四"},{"title":"伤情怨/清商怨"},{"title":"华胥引"},{"title":"庆春宫/高阳台"},{"title":"扫花游/扫地游 雷峰落照"},{"title":"扫花游/扫地游"},{"title":"早梅芳 其二"},{"title":"早梅芳/喜迁莺 其一"},{"title":"江城子"},{"title":"百字令 断桥残雪"},{"title":"红林檎近 其一"},{"title":"红林檎近 其二"},{"title":"红罗袄"},{"title":"西平乐慢/西平乐"},{"title":"西河"},{"title":"西湖明月引/江城梅花引 寿云谷谢右司"},{"title":"过秦楼 寿建安使君谢右司"},{"title":"选冠子 其二"},{"title":"选冠子 其一"},{"title":"齐天乐 南屏晚钟"},{"title":"齐天乐"},{"title":"齐天乐 泽国楼偶赋"},{"title":"应天长"},{"title":"花犯"},{"title":"芳草渡/系裙腰"},{"title":"诉衷情令 其一"},{"title":"诉衷情令 其二"},{"title":"迎春乐 其二"},{"title":"迎春乐 其三"},{"title":"迎春乐 其一"},{"title":"还京乐"},{"title":"侧犯"},{"title":"垂丝钓"},{"title":"垂杨"},{"title":"夜飞鹊/夜飞鹊慢"},{"title":"夜游宫 其二"},{"title":"夜游宫 其一"},{"title":"定风波"},{"title":"宝鼎见/宝鼎现 云岩师书灯夕命赋"},{"title":"明月引/江城梅花引 和白云赵宗簿自度曲"},{"title":"法曲献仙音"},{"title":"法曲献仙音 寿云谷谢秘撰"},{"title":"青玉案 采莲女"},{"title":"临江仙 寿千八兄"},{"title":"南乡子"},{"title":"南歌子"},{"title":"南歌子 茉莉"},{"title":"品令"},{"title":"思佳客 和俞菊坡海棠韵"},{"title":"思佳客 其一 用晏小山韵"},{"title":"思佳客 其五"},{"title":"思佳客 其四"},{"title":"思佳客 其三"},{"title":"思佳客 其二"},{"title":"拜星月慢"},{"title":"昼锦堂 北城韩园即事"},{"title":"柳梢青 和逃禅四首 其一"},{"title":"柳梢青 其二"},{"title":"柳梢青 其四"},{"title":"柳梢青 其三"},{"title":"点绛唇 其四"},{"title":"点绛唇 其二"},{"title":"点绛唇 其三"},{"title":"点绛唇 其一"},{"title":"玲珑四犯"},{"title":"琴调相思引"},{"title":"祝英台近"},{"title":"秋霁 平湖秋月"},{"title":"秋蕊香"},{"title":"绕佛阁"},{"title":"绛都春 旧上声韵，今改平声"},{"title":"荔枝香近 其一"},{"title":"荔枝香近 其二"},{"title":"倒犯"},{"title":"倦寻芳"},{"title":"宴桃源/如梦令 其一"},{"title":"宴桃源/如梦令 其二"},{"title":"宴清都"},{"title":"恋绣衾"},{"title":"桂枝香 杨山甫席上赋"},{"title":"浣溪沙 其五"},{"title":"浣溪沙 其七"},{"title":"浣溪沙 其三"},{"title":"浣溪沙 其九"},{"title":"浣溪沙 其一"},{"title":"浣溪沙 其八"},{"title":"浣溪沙 其二"},{"title":"浣溪沙 其六"},{"title":"浣溪沙"},{"title":"浣溪沙 其四"},{"title":"浪淘沙慢"},{"title":"婆罗门引 两峰插云"},{"title":"尉迟杯"},{"title":"惜分飞"},{"title":"探春/探春慢 苏堤春晓"},{"title":"清平乐"},{"title":"渔家傲 其一"},{"title":"渔家傲 其二"},{"title":"琐窗寒"},{"title":"绮罗香 秋雨"},{"title":"绮寮怨"},{"title":"菩萨蛮"},{"title":"黄莺儿 柳浪闻莺"},{"title":"朝中措"},{"title":"渡江云"},{"title":"渡江云 寿蔡泉使"},{"title":"渡江云 三潭印月"},{"title":"疏影"},{"title":"隔浦莲近拍"},{"title":"塞垣春"},{"title":"塞翁吟"},{"title":"意难忘"},{"title":"感皇恩"},{"title":"摸鱼儿 西湖送春"},{"title":"摸鱼儿 寿叶制相"},{"title":"暗香"},{"title":"满江红"},{"title":"满庭芳"},{"title":"满路花/促拍满路花 其一"},{"title":"满路花/促拍满路花 其二"},{"title":"瑞龙吟 寿吴丞相"},{"title":"瑞龙吟"},{"title":"瑞鹤仙"},{"title":"蓦山溪 花港观鱼"},{"title":"虞美人 其四"},{"title":"虞美人 其三"},{"title":"虞美人 其一"},{"title":"虞美人 其二"},{"title":"虞美人 其五"},{"title":"解连环"},{"title":"解语花"},{"title":"解蹀躞"},{"title":"酹江月/念奴娇"},{"title":"酹江月/念奴娇 赋水仙"},{"title":"蕙兰芳引"},{"title":"蝶恋花 其一"},{"title":"蝶恋花 其四"},{"title":"蝶恋花 其五"},{"title":"蝶恋花 其二"},{"title":"蝶恋花 其三"},{"title":"醉桃源 其二"},{"title":"醉桃源 其一"},{"title":"醉桃源"},{"title":"醉蓬莱 寿越帅谢恕斋"},{"title":"糖多令/唐多令 桂边偶成"},{"title":"糖多令/唐多令 吴江道上赠郑可大"},{"title":"糖多令/唐多令 秋暮有感"},{"title":"鹧鸪天 寿表兄陈可大"},{"title":"鹧鸪天"},{"title":"霜天晓角 寿疏清陈别驾"},{"title":"霜天晓角"},{"title":"谒金门 其三"},{"title":"风流子"},{"title":"早梅芳/喜迁莺"},{"title":"荔枝香近"},{"title":"玉楼春"},{"title":"宴桃源/如梦令"},{"title":"渔家傲"},{"title":"蝶恋花"},{"title":"少年游"},{"title":"选冠子"},{"title":"红林檎近"},{"title":"满路花/促拍满路花"},{"title":"点绛唇"},{"title":"夜游宫"},{"title":"诉衷情令"},{"title":"一落索"},{"title":"迎春乐"},{"title":"虞美人"}]}